yqml/__init__.py
yqml/cte.py
yqml/field.py
yqml/fields.py
yqml/file.py
yqml/join.py
yqml/joins.py
yqml/keys.py
yqml/merge.py
yqml/query.py
yqml/select.py
yqml/where.py
yqml/yqml.py
yqml-0.0.2.dist-info/LICENSE
yqml-0.0.2.dist-info/METADATA
yqml-0.0.2.dist-info/WHEEL
yqml-0.0.2.dist-info/top_level.txt
yqml-0.0.2.dist-info/RECORD
