Metadata-Version: 2.1
Name: yqml
Version: 0.0.2
Summary: YAML based query language
Home-page: https://github.com/maztohir/yqml
Author: Muhamad Tohir
Author-email: maztohir@gmail.com
License: UNKNOWN
Keywords: sql,python,query,yaml
Platform: UNKNOWN
Classifier: Development Status :: 2 - Pre-Alpha
Classifier: Intended Audience :: Developers
Classifier: License :: OSI Approved :: MIT License
Classifier: Operating System :: Unix
Classifier: Operating System :: POSIX
Classifier: Operating System :: Microsoft :: Windows
Classifier: Programming Language :: Python :: 3
Requires-Python: >=3.6
Requires-Dist: PyYAML (==5.4.1)
